{
  "assignments": [
    {
      "id": "Eswanth-2025-12-29-1767167076520",
      "engineerName": "Eswanth",
      "weekStart": "2025-12-29",
      "projectName": "3W-SA1-25061_CELL1",
      "projectTargetDate": "2026-01-03",
      "tasks": [
        {
          "id": "task-1767167099021",
          "taskName": "IO CHECK",
          "targetDate": "2025-12-31",
          "completionDate": "",
          "status": "not_started"
        },
        {
          "id": "task-1767167116766",
          "taskName": "EIP CONFIGURATION",
          "targetDate": "2025-12-31",
          "completionDate": "",
          "status": "not_started"
        },
        {
          "id": "task-1767167134051",
          "taskName": "ROBOT COMMUNICATION",
          "targetDate": "2026-01-01",
          "completionDate": "",
          "status": "not_started"
        },
        {
          "id": "task-1767167145124",
          "taskName": "IO CHECK",
          "targetDate": "2026-01-01",
          "completionDate": "",
          "status": "not_started"
        },
        {
          "id": "task-1767167170714",
          "taskName": "MANUAL SEQUENCE CHECK",
          "targetDate": "2026-01-01",
          "completionDate": "",
          "status": "not_started"
        }
      ],
      "currentStatus": "in_progress",
      "notes": "R1J2 IO MAPPING,EIP CONFIGURATION,ROBOT MAPPING,IO CHECK"
    }
  ],
  "lastUpdated": "2025-12-31T07:46:11.118Z"
}